disops/Charlier.py
disops/Hahn.py
disops/Krawtchouk.py
disops/Meixner.py
disops/OrthogonalPolynomialsGenerator.py
disops/__init__.py
disops-1.1.1.dist-info/LICENSE
disops-1.1.1.dist-info/METADATA
disops-1.1.1.dist-info/WHEEL
disops-1.1.1.dist-info/top_level.txt
disops-1.1.1.dist-info/RECORD
