Metadata-Version: 2.1
Name: disops
Version: 1.1.1
Summary: Orthogonal Polynomials of a Discrete Variable
Home-page: https://gitlab.com/joselruiz/tfg/-/tree/main/disops
Author: José L. Ruiz
License: GNU GPLv3 
Requires-Python: >=3.8
License-File: LICENSE
Requires-Dist: sympy (>=1.10.1)
Requires-Dist: matplotlib (>=3.5.1)
